<?xml version="1.0" encoding="UTF-8"?>
<LanguageData>
  
  <!-- EN: crab -->
  <Crab.label>krab</Crab.label>
  <!-- EN: left eye -->
  <Crab.corePart.parts.HeadWithEarHoles.parts.left_eye.customLabel>levé oko</Crab.corePart.parts.HeadWithEarHoles.parts.left_eye.customLabel>
  <!-- EN: right eye -->
  <Crab.corePart.parts.HeadWithEarHoles.parts.right_eye.customLabel>pravé oko</Crab.corePart.parts.HeadWithEarHoles.parts.right_eye.customLabel>
  <!-- EN: left claw -->
  <Crab.corePart.parts.left_claw.customLabel>levé klepeto</Crab.corePart.parts.left_claw.customLabel>
  <!-- EN: right claw -->
  <Crab.corePart.parts.right_claw.customLabel>pravé klepeto</Crab.corePart.parts.right_claw.customLabel>
  <!-- EN: left first leg -->
  <Crab.corePart.parts.left_first_leg.customLabel>levá první noha</Crab.corePart.parts.left_first_leg.customLabel>
  <!-- EN: right first leg -->
  <Crab.corePart.parts.right_first_leg.customLabel>pravá první noha</Crab.corePart.parts.right_first_leg.customLabel>
  <!-- EN: left second leg -->
  <Crab.corePart.parts.left_second_leg.customLabel>levá druhá noha</Crab.corePart.parts.left_second_leg.customLabel>
  <!-- EN: right second leg -->
  <Crab.corePart.parts.right_second_leg.customLabel>pravá druhá noha</Crab.corePart.parts.right_second_leg.customLabel>
  <!-- EN: left third leg -->
  <Crab.corePart.parts.left_third_leg.customLabel>levá třetí noha</Crab.corePart.parts.left_third_leg.customLabel>
  <!-- EN: right third leg -->
  <Crab.corePart.parts.right_third_leg.customLabel>pravá třetí noha</Crab.corePart.parts.right_third_leg.customLabel>
  <!-- EN: left swimming leg -->
  <Crab.corePart.parts.left_swimming_leg.customLabel>levá plavecká noha</Crab.corePart.parts.left_swimming_leg.customLabel>
  <!-- EN: right swimming leg -->
  <Crab.corePart.parts.right_swimming_leg.customLabel>pravá plavecká noha</Crab.corePart.parts.right_swimming_leg.customLabel>
  
</LanguageData>