<?xml version="1.0" encoding="UTF-8"?>
<LanguageData>
  
  <!-- EN: Apparel -->
  <Apparel.label>Oblečení</Apparel.label>
  
  <!-- EN: Basics -->
  <Basics.label>Základ</Basics.label>
  
  <!-- EN: Basics -->
  <BasicsNonPawn.label>Základ</BasicsNonPawn.label>
  
  <!-- EN: Basics -->
  <BasicsPawn.label>Základ</BasicsPawn.label>
  
  <!-- EN: Building -->
  <Building.label>Stavba</Building.label>
  
  <!-- EN: Offsets when equipped -->
  <EquippedStatOffsets.label>Modifikátor při vybavení předmětem</EquippedStatOffsets.label>
  
  <!-- EN: Combat -->
  <PawnCombat.label>Boj</PawnCombat.label>
  
  <!-- EN: Misc -->
  <PawnMisc.label>Ostatní</PawnMisc.label>
  
  <!-- EN: Social -->
  <PawnSocial.label>Socializace</PawnSocial.label>
  
  <!-- EN: Work -->
  <PawnWork.label>Činnosti</PawnWork.label>
  
  <!-- EN: Multipliers when equipment made of this -->
  <StuffOfEquipmentStatFactors.label>Multiplikátor, když je vybavení z tohoto materiálu</StuffOfEquipmentStatFactors.label>
  
  <!-- EN: Multipliers when made of this -->
  <StuffStatFactors.label>Násobitele pro tento materiál</StuffStatFactors.label>
  
  <!-- EN: Offsets when made of this -->
  <StuffStatOffsets.label>Bonusy a postihy pro tento materiál</StuffStatOffsets.label>
  
  <!-- EN: Surgical -->
  <Surgery.label>Chirurgický</Surgery.label>
  
  <!-- EN: Weapon -->
  <Weapon.label>Zbraň</Weapon.label>
  
</LanguageData>