<?xml version="1.0" encoding="utf-8"?>
<LanguageData>

  <Consciousness.label>vědomí</Consciousness.label>
  <Consciousness.labelMechanoids>zpracování dat</Consciousness.labelMechanoids>

  <Moving.label>pohyb</Moving.label>
  <Manipulation.label>manipulace</Manipulation.label>

  <Talking.label>řeč</Talking.label>
  <Talking.labelMechanoids>komunikace</Talking.labelMechanoids>

  <Eating.label>stravování</Eating.label>
  <Sight.label>zrak</Sight.label>
  <Hearing.label>sluch</Hearing.label>
  <Breathing.label>dýchání</Breathing.label>
  <BloodFiltration.label>filtrace krve</BloodFiltration.label>
  <BloodPumping.label>cirkulace krve</BloodPumping.label>
  <Metabolism.label>metabolismus</Metabolism.label>

</LanguageData>
