<?xml version="1.0" encoding="UTF-8"?>
<LanguageData>

  <!-- Xenogerm -->
  <!-- EN: Select icon -->
  <SelectIcon>Výběr ikony</SelectIcon>
  <!-- EN: The icon of this xenotype. -->
  <SelectIconDesc>Ikona tohoto xenotypu.</SelectIconDesc>
  <!-- EN: Start combining -->
  <StartCombining>Zahájit kombinování</StartCombining>
  <!-- EN: Click to add or remove -->
  <ClickToAddOrRemove>Pro přidání nebo odebrání klikni</ClickToAddOrRemove>
  <!-- EN: Click to add -->
  <ClickToAdd>Pro přidání klikni</ClickToAdd>
  <!-- EN: Click to remove -->
  <ClickToRemove>Pro odebrání klikni</ClickToRemove>
  <!-- EN: xenotype name -->
  <XenotypeName>Název xenotypu</XenotypeName>

  <!-- Xenogerm editor -->
  <!-- EN: Load template -->
  <LoadXenogermTemplate>Načíst šablonu</LoadXenogermTemplate>
  <!-- EN: Save template -->
  <SaveXenogermTemplate>Uložit šablonu</SaveXenogermTemplate>
  <!-- EN: {NAME} template saved -->
  <XenogermTemplateSaved>Šablona uložena pod názvem {NAME}</XenogermTemplateSaved>
  <!-- Mechs -->
  <!-- EN: Weight class -->
  <MechWeightClass>Váhová kategorie</MechWeightClass>
  <!-- EN: The weight class of this mech. -->
  <MechWeightClassExplanation>Váhová kategorie tohoto mecha.</MechWeightClassExplanation>
  <!-- EN: This mech's overseer is {0}. -->
  <MechOverseer>{0_gender ? Dohlížitelem : Dohlížitelkou} tohoto mecha je {0}.</MechOverseer>
  <!-- EN: Your caravan contains a mechanoid but not their overseer. You will have limited control over the mechanoid when you reach your destination. -->
  <CaravanLacksMechMechanitorWarning>Tvá karavana zahrnuje nejméně jednoho mechanoida, ale žádného dohlížitele. Až dorazíš do cíle, budeš mít nad mechanoidy omezenou kontrolu.</CaravanLacksMechMechanitorWarning>
  <!-- EN: Mechanoids -->
  <MechsSection>Mechanoidi</MechsSection>

  <!-- Pawn naming -->
  <!-- EN: Rename mech -->
  <RenameMech>Přejmenovat mecha</RenameMech>
  <!-- EN: The mech's name is now {0}. -->
  <MechGainsName>Mech se nyní jmenuje {0}.</MechGainsName>

  <!-- EN: Choose mech accent color -->
  <ChooseMechAccentColor>Výběr barevného zvýraznění mechů</ChooseMechAccentColor>

</LanguageData>