<?xml version="1.0" encoding="utf-8"?>
<LanguageData>

	<Maneuver_Slash.rulePack.rulesStrings>
		<li>damaged_inf(p=4)->pořezat</li>
		<li>damaged_inf->říznout</li>
		<li>damaged_inf->nasekat</li>
		<li>damaged_inf->seknout</li>
		<li>damaged_inf->nakrájet</li>
		<li>damaged_inf->naříznout</li>
		<li>damaged_past(p=4)->pořezal</li>
		<li>damaged_past->řízl</li>
		<li>damaged_past->sekl</li>
		<li>damaged_past->nasekl</li>
		<li>damaged_past->nakrojil</li>
		<li>damaged_past->nařízl</li>
		<li>damaged_present->pořezání</li>
		<li>damaged_present->přeříznutí</li>
		<li>damaged_present->nakrojení</li>
		<li>damaged_present->naříznutí</li>
		<li>damaged_present->natržení</li>
		<li>damaged_present->potrhání</li>
		<li>woundname->rány</li>
		<li>woundname(p=0.3)->otevřené rány</li>
		<li>flavortextsituation(recipient_flesh!=Mechanoid)->Útok u oběti započal silné krvácení z [woundname]</li>
		<li>flavortextsituation->Z [woundname] na těle oběti začaly odkapávat tělní tekutiny</li>
		<li>flavortextconsequence(recipient_flesh!=Mechanoid)->Řezná rána odkryla maso</li>
		<li>flavortextconsequence(recipient_flesh==Mechanoid)->Řezná rána odhalila vnitřní strojní mechanismy</li>
		<li>flavortextconsequence(recipient_flesh!=Mechanoid)->Na těle oběti byla zanechána hrůzná rána</li>
		<li>destroyed_past->rozkouskoval</li>
		<li>destroyed_past->přepůlil</li>
		<li>destroyed_past->rozpůlil</li>
		<li>destroyed_past->přesekl</li>
		<li>destroyed_past->rozštěpil</li>
		<li>destroyed_present->rozkouskování</li>
		<li>destroyed_present->přepůlení</li>
		<li>destroyed_present->rozpůlení</li>
		<li>destroyed_present->přeseknutí</li>
		<li>destroyed_present->rozštěpení</li>
		<li>destroyed_suffix->Útokem bylo provedeno nasekání do úhledných kousků</li>
		<li>destroyed_suffix->Útok byl proveden čistým zásahem</li>
		<li>destroyed_suffix(target_part_destroyed_count==1)->Útok odhalil, jak uvnitř funguje</li>
		<li>destroyed_suffix(target_part_destroyed_count==1)->Útok způsobil rozdělení ve dvoj</li>
	</Maneuver_Slash.rulePack.rulesStrings>

	<Maneuver_Stab.rulePack.rulesStrings>
		<li>damaged_inf(p=4)->probodnout</li>
		<li>damaged_inf->bodnout</li>
		<li>damaged_inf->pobodat</li>
		<li>damaged_inf->propíchnout</li>
		<li>damaged_inf->nabodnout</li>
		<li>damaged_past(p=4)->probodl</li>
		<li>damaged_past->bodl</li>
		<li>damaged_past->bodnul</li>
		<li>damaged_past->propíchl</li>
		<li>damaged_past->probodl</li>
		<li>damaged_present->nabodnutí</li>
		<li>damaged_present->probodání</li>
		<li>damaged_present->propíchnutí</li>
		<li>damaged_present->probodnutí</li>
		<li>woundname->díra</li>
		<li>woundname->rána</li>
		<li>woundname->štěrbina</li>
		<li>flavortextconsequence(recipient_flesh!=Mechanoid)->Na těle oběti byla zanechána krvavá [woundname]</li>
		<li>flavortextconsequence(recipient_flesh!=Mechanoid)->Na těle oběti byla zanechána rozervaná [woundname]</li>
		<li>flavortextconsequence(recipient_flesh!=Mechanoid)->Na těle oběti byla zanechána krvácející [woundname]</li>
		<li>destroyed_past->rozpíchal</li>
		<li>destroyed_past->proděravěl</li>
		<li>destroyed_past->rozrýpal</li>
		<li>destroyed_present->rozpíchání</li>
		<li>destroyed_present->proděravění</li>
		<li>destroyed_present->rozrýpání</li>
		<li>destroyed_suffix->Útok byl proveden skrz naskrz</li>
		<li>destroyed_suffix->Útok zanechal čistou díru</li>
		<li>destroyed_suffix(recipient_flesh!=Mechanoid,target_part_destroyed_count==1)->Útok způsobil únik provozních kapalin</li>
		<li>destroyed_suffix(target_part_destroyed_count==1)->Útok způsobil únik neurčitelných kapalin</li>
	</Maneuver_Stab.rulePack.rulesStrings>

	<Maneuver_Smash_Damage.rulePack.rulesStrings>
		<li>damaged_inf(p=4)->udeřit</li>
		<li>damaged_inf->praštit</li>
		<li>damaged_inf->zasáhnout</li>
		<li>damaged_inf->bouchnout</li>
		<li>damaged_inf->uhodit</li>
		<li>damaged_past(p=4)->udeřil</li>
		<li>damaged_past->praštil</li>
		<li>damaged_past->zasáhl</li>
		<li>damaged_past->bouchl</li>
		<li>damaged_past->uhodil</li>
		<li>damaged_present->zhmoždění</li>
		<li>damaged_present->poranění</li>
		<li>damaged_present->pochroumání</li>
		<li>damaged_present->pohmoždění</li>
		<li>damaged_present->natržení</li>
		<li>destroyed_past->roztříštil</li>
		<li>destroyed_past->rozdrtil</li>
		<li>destroyed_past->zruinoval</li>
		<li>destroyed_past->zničil</li>
		<li>destroyed_past->rozlámal</li>
		<li>destroyed_present->roztříštění</li>
		<li>destroyed_present->rozdrcení</li>
		<li>destroyed_present->zruinování</li>
		<li>destroyed_present->zničení</li>
		<li>destroyed_present->rozlámání</li>
	</Maneuver_Smash_Damage.rulePack.rulesStrings>

	<Maneuver_Smash.rulePack.rulesStrings>
		<li>flavortextconsequence(recipient_flesh!=Mechanoid)->Na těle oběti byla zanechána obrovská podlitina</li>
		<li>flavortextconsequence->Na těle oběti bylo zanecháno viditelně zdeformované místo</li>
		<li>flavortextconsequence->Oběť úderem ztratila rovnováhu</li>
		<li>flavortextconsequence->Oběť byla úderem sražena na stranu</li>
		<li>destroyed_suffix->Útokem bylo způsobeno rozdělení [to] kusy</li>
		<li>destroyed_suffix->Útokem bylo způsobeno rozdrcení [to] padrť</li>
		<li>destroyed_suffix(recipient_flesh!=Mechanoid)->Útokem bylo způsobeno rozmašírování [to] jemnou kaši</li>
		<li>destroyed_suffix->Útokem bylo způsobeno rozdrcení [to] části</li>
	</Maneuver_Smash.rulePack.rulesStrings>

	<Maneuver_Scratch_Damage.rulePack.rulesStrings>
		<li>damaged_inf(p=4)->poškrábat</li>
		<li>damaged_inf->rozdrásat</li>
		<li>damaged_inf->vyškrábat</li>
		<li>damaged_inf->podrápat</li>
		<li>damaged_past(p=4)->poškrábal</li>
		<li>damaged_past->rozdrásal</li>
		<li>damaged_past->rozškrábal</li>
		<li>damaged_past->podrápal</li>
		<li>damaged_present->poškábání</li>
		<li>damaged_present->rozdrásání</li>
		<li>damaged_present->rozškrábání</li>
		<li>damaged_present->podrápání</li>
		<li>destroyed_past->rozerval</li>
		<li>destroyed_past->roztrhal</li>
		<li>destroyed_past->vytrhl</li>
		<li>destroyed_past->rozškubal</li>
		<li>destroyed_past->rozpáral</li>
		<li>destroyed_present->rozervání</li>
		<li>destroyed_present->roztrhání</li>
		<li>destroyed_present->vytržení</li>
		<li>destroyed_present->rozškubání</li>
		<li>destroyed_present->rozpárání</li>
	</Maneuver_Scratch_Damage.rulePack.rulesStrings>

	<Maneuver_Scratch.rulePack.rulesStrings>
		<li>woundname->rány</li>
		<li>woundname(p=0.3)->otevřené rány</li>
		<li>flavortextsituation(recipient_flesh!=Mechanoid)->Útok u oběti započal silné krvácení z [woundname]</li>
		<li>flavortextsituation->Z [woundname] na těle oběti začaly odkapávat tělní tekutiny</li>
		<li>flavortextconsequence(recipient_flesh!=Mechanoid)->Tržná rána odkryla maso</li>
		<li>flavortextconsequence(recipient_flesh==Mechanoid)->Tržná rána odhalila vnitřní strojní mechanismy</li>
		<li>flavortextconsequence(recipient_flesh!=Mechanoid)->Na těle oběti byla zanechána hrůzná rána</li>
		<li>destroyed_suffix(recipient_flesh!=Mechanoid)->Útokem bylo provedeno rozpárání [to] rozmašírované proužky</li>
		<li>destroyed_suffix->Útokem bylo provedeno rozpárání [to] proužky</li>
		<li>destroyed_suffix(recipient_flesh!=Mechanoid)->Útokem bylo provedeno rozporcování [to] rozmašírované kousky</li>
		<li>destroyed_suffix->Útokem bylo způsobeno rozdělení [to] kusy</li>
		<li>destroyed_suffix->Útokem bylo způsobeno rozmašírování [to] kousíčky</li>
		<li>destroyed_suffix(recipient_flesh!=Mechanoid)->Útokem bylo způsobeno rozškrábání [to] hromadu sraženiny</li>
	</Maneuver_Scratch.rulePack.rulesStrings>

	<Poke.rulePack.rulesStrings>
		<li>damaged_inf(p=2)->píchnout</li>
		<li>damaged_inf(p=2)->bodnout</li>
		<li>damaged_inf->dloubnout</li>
		<li>damaged_inf->šťouchnout</li>
		<li>damaged_inf->probodnout</li>
		<li>damaged_past(p=2)->píchl</li>
		<li>damaged_past(p=2)->bodl</li>
		<li>damaged_past->dloubl</li>
		<li>damaged_past->šťouchl</li>
		<li>damaged_past->drcl</li>
		<li>damaged_present(p=2)->píchnutí</li>
		<li>damaged_present(p=2)->bodnutí</li>
		<li>damaged_present->pohmoždění</li>
		<li>damaged_present->namožení</li>
		<li>damaged_present->nabodnutí</li>
		<li>flavortextconsequence(recipient_flesh!=Mechanoid)->Na těle oběti byla zanechána obrovská podlitina</li>
		<li>flavortextconsequence->Na těle oběti bylo zanecháno viditelně zdeformované místo</li>
		<li>flavortextconsequence->Oběť úderem ztratila rovnováhu</li>
		<li>flavortextconsequence->Oběť byla úderem sražena na stranu</li>
		<li>destroyed_past->roztříštil</li>
		<li>destroyed_past->rozdrtil</li>
		<li>destroyed_past->zruinoval</li>
		<li>destroyed_past->zničil</li>
		<li>destroyed_past->rozlámal</li>
		<li>destroyed_present->roztříštění</li>
		<li>destroyed_present->rozdrcení</li>
		<li>destroyed_present->zruinování</li>
		<li>destroyed_present->zničení</li>
		<li>destroyed_present->rozlámání</li>
		<li>destroyed_suffix->Útokem bylo způsobeno rozdělení [to] kusy</li>
		<li>destroyed_suffix->Útokem bylo způsobeno rozdrcení [to] padrť</li>
		<li>destroyed_suffix(recipient_flesh!=Mechanoid)->Útokem bylo způsobeno rozmašírování [to] jemnou kaši</li>
		<li>destroyed_suffix->Útokem bylo způsobeno rozdělení [to] části</li>
	</Poke.rulePack.rulesStrings>

	<Bite.rulePack.rulesStrings>
		<li>damaged_inf->kousnout</li>
		<li>damaged_inf->hryznout</li>
		<li>damaged_inf(p=0.5)->štípnout</li>
		<li>damaged_past->kousl</li>
		<li>damaged_past->hryzl</li>
		<li>damaged_past->štípl</li>
		<li>damaged_past->rafl</li>
		<li>damaged_past->natrhl</li>
		<li>damaged_present->nakousnutí</li>
		<li>damaged_present->nahryznutí</li>
		<li>damaged_present->našťípnutí</li>
		<li>damaged_present->rafnutí</li>
		<li>damaged_present->natržení</li>
		<li>flavortextconsequence(recipient_flesh!=Mechanoid)->Tržná rána odkryla maso</li>
		<li>flavortextconsequence(recipient_flesh==Mechanoid)->Tržná rána odhalila vnitřní strojní mechanismy</li>
		<li>flavortextconsequence(recipient_flesh!=Mechanoid)->Na kůži oběti byly zanechány hrůzné rány od kousnutí</li>
		<li>flavortextconsequence(recipient_flesh==Mechanoid)->Na plechu oběti byly zanechány ošklivé rány od kousnutí</li>
		<li>destroyed_past->sežral</li>
		<li>destroyed_past->oddělil</li>
		<li>destroyed_past->rozpáral</li>
		<li>destroyed_past->zdevastoval</li>
		<li>destroyed_present->sežrání</li>
		<li>destroyed_present->oddělení</li>
		<li>destroyed_present->rozpárání</li>
		<li>destroyed_present->zdevastování</li>
		<li>destroyed_suffix->Útokem bylo způsobeno rozkousání [to] malé kousky</li>
		<li>destroyed_suffix->Útokem bylo způsobeno roztrhání [to] kusy</li>
		<li>destroyed_suffix->Útokem bylo způsobeno rozpárání [to] proužky</li>
		<li>destroyed_suffix(recipient_flesh!=Mechanoid)->Útokem bylo způsobeno roztrhání [to] rozmašírované proužky</li>
		<li>destroyed_suffix(recipient_flesh!=Mechanoid)->Útokem bylo způsobeno rozškubání [to] nepoužitelnou kaši</li>
	</Bite.rulePack.rulesStrings>


</LanguageData>