<?xml version="1.0" encoding="utf-8"?>
<LanguageData>

  <Blueprint_Concrete.label>beton (plán)</Blueprint_Concrete.label>
  <Frame_Concrete.label>beton (ve výstavbě)</Frame_Concrete.label>
  <Frame_Concrete.description>Probíhající podlahové práce.</Frame_Concrete.description>

  <Blueprint_PavedTile.label>betonové dlaždice (plán)</Blueprint_PavedTile.label>
  <Frame_PavedTile.label>betonové dlaždice (ve výstavbě)</Frame_PavedTile.label>
  <Frame_PavedTile.description>Probíhající podlahové práce.</Frame_PavedTile.description>

  <Blueprint_WoodPlankFloor.label>dřevěná podlaha (plán)</Blueprint_WoodPlankFloor.label>
  <Frame_WoodPlankFloor.label>dřevěná podlaha (ve výstavbě)</Frame_WoodPlankFloor.label>
  <Frame_WoodPlankFloor.description>Probíhající podlahové práce.</Frame_WoodPlankFloor.description>

  <Blueprint_MetalTile.label>ocelové pláty (plán)</Blueprint_MetalTile.label>
  <Frame_MetalTile.label>ocelové pláty (ve výstavbě)</Frame_MetalTile.label>
  <Frame_MetalTile.description>Probíhající podlahové práce.</Frame_MetalTile.description>

  <Blueprint_SilverTile.label>stříbrné dlaždice (plán)</Blueprint_SilverTile.label>
  <Frame_SilverTile.label>stříbrné dlaždice (ve výstavbě)</Frame_SilverTile.label>
  <Frame_SilverTile.description>Probíhající podlahové práce.</Frame_SilverTile.description>

  <Blueprint_GoldTile.label>zlaté dlaždice (plán)</Blueprint_GoldTile.label>
  <Frame_GoldTile.label>zlaté dlaždice (ve výstavbě)</Frame_GoldTile.label>
  <Frame_GoldTile.description>Probíhající podlahové práce.</Frame_GoldTile.description>

  <Blueprint_SterileTile.label>sterilní dlaždice (plán)</Blueprint_SterileTile.label>
  <Frame_SterileTile.label>sterilní dlaždice (ve výstavbě)</Frame_SterileTile.label>
  <Frame_SterileTile.description>Probíhající podlahové práce.</Frame_SterileTile.description>

  <Blueprint_CarpetRed.label>červený koberec (plán)</Blueprint_CarpetRed.label>
  <Frame_CarpetRed.label>červený koberec (ve výstavbě)</Frame_CarpetRed.label>
  <Frame_CarpetRed.description>Probíhající podlahové práce.</Frame_CarpetRed.description>

  <Blueprint_CarpetGreen.label>zelený koberec (plán)</Blueprint_CarpetGreen.label>
  <Frame_CarpetGreen.label>zelený koberec (ve výstavbě)</Frame_CarpetGreen.label>
  <Frame_CarpetGreen.description>Probíhající podlahové práce.</Frame_CarpetGreen.description>

  <Blueprint_CarpetBlue.label>modrý koberec (plán)</Blueprint_CarpetBlue.label>
  <Frame_CarpetBlue.label>modrý koberec (ve výstavbě)</Frame_CarpetBlue.label>
  <Frame_CarpetBlue.description>Probíhající podlahové práce.</Frame_CarpetBlue.description>

  <Blueprint_CarpetCream.label>krémový koberec (plán)</Blueprint_CarpetCream.label>
  <Frame_CarpetCream.label>krémový koberec (ve výstavbě)</Frame_CarpetCream.label>
  <Frame_CarpetCream.description>Probíhající podlahové práce.</Frame_CarpetCream.description>

  <Blueprint_CarpetDark.label>tmavý koberec (plán)</Blueprint_CarpetDark.label>
  <Frame_CarpetDark.label>tmavý koberec (ve výstavbě)</Frame_CarpetDark.label>
  <Frame_CarpetDark.description>Probíhající podlahové práce.</Frame_CarpetDark.description>

  <Blueprint_TileSandstone.label>pískovcové dlaždice (plán)</Blueprint_TileSandstone.label>
  <Frame_TileSandstone.label>pískovcové dlaždice (ve výstavbě)</Frame_TileSandstone.label>
  <Frame_TileSandstone.description>Probíhající podlahové práce.</Frame_TileSandstone.description>

  <Blueprint_TileGranite.label>žulové dlaždice (plán)</Blueprint_TileGranite.label>
  <Frame_TileGranite.label>žulové dlaždice (ve výstavbě)</Frame_TileGranite.label>
  <Frame_TileGranite.description>Probíhající podlahové práce.</Frame_TileGranite.description>

  <Blueprint_TileLimestone.label>vápencové dlaždice (plán)</Blueprint_TileLimestone.label>
  <Frame_TileLimestone.label>vápencové dlaždice (ve výstavbě)</Frame_TileLimestone.label>
  <Frame_TileLimestone.description>Probíhající podlahové práce.</Frame_TileLimestone.description>

  <Blueprint_TileSlate.label>břidlicové dlaždice (plán)</Blueprint_TileSlate.label>
  <Frame_TileSlate.label>břidlicové dlaždice (ve výstavbě)</Frame_TileSlate.label>
  <Frame_TileSlate.description>Probíhající podlahové práce.</Frame_TileSlate.description>

  <Blueprint_TileMarble.label>mramorové dlaždice (plán)</Blueprint_TileMarble.label>
  <Frame_TileMarble.label>mramorové dlaždice (ve výstavbě)</Frame_TileMarble.label>
  <Frame_TileMarble.description>Probíhající podlahové práce.</Frame_TileMarble.description>

  <Blueprint_FlagstoneSandstone.label>pískovcové dlažební kameny (plán)</Blueprint_FlagstoneSandstone.label>
  <Frame_FlagstoneSandstone.label>pískovcové dlažební kameny (ve výstavbě)</Frame_FlagstoneSandstone.label>
  <Frame_FlagstoneSandstone.description>Probíhající podlahové práce.</Frame_FlagstoneSandstone.description>

  <Blueprint_FlagstoneGranite.label>žulové dlažební kameny (plán)</Blueprint_FlagstoneGranite.label>
  <Frame_FlagstoneGranite.label>žulové dlažební kameny (ve výstavbě)</Frame_FlagstoneGranite.label>
  <Frame_FlagstoneGranite.description>Probíhající podlahové práce.</Frame_FlagstoneGranite.description>

  <Blueprint_FlagstoneLimestone.label>vápencové dlažební kameny (plán)</Blueprint_FlagstoneLimestone.label>
  <Frame_FlagstoneLimestone.label>vápencové dlažební kameny (ve výstavbě)</Frame_FlagstoneLimestone.label>
  <Frame_FlagstoneLimestone.description>Probíhající podlahové práce.</Frame_FlagstoneLimestone.description>

  <Blueprint_FlagstoneSlate.label>břidlicové dlažební kameny (plán)</Blueprint_FlagstoneSlate.label>
  <Frame_FlagstoneSlate.label>břidlicové dlažební kameny (ve výstavbě)</Frame_FlagstoneSlate.label>
  <Frame_FlagstoneSlate.description>Probíhající podlahové práce.</Frame_FlagstoneSlate.description>

  <Blueprint_FlagstoneMarble.label>mramorové dlažební kameny (plán)</Blueprint_FlagstoneMarble.label>
  <Frame_FlagstoneMarble.label>mramorové dlažební kameny (ve výstavbě)</Frame_FlagstoneMarble.label>
  <Frame_FlagstoneMarble.description>Probíhající podlahové práce.</Frame_FlagstoneMarble.description>

  <Blueprint_Bridge.label>most (plán)</Blueprint_Bridge.label>
  <Frame_Bridge.label>most (ve výstavbě)</Frame_Bridge.label>
  <Frame_Bridge.description>Probíhající stavební práce.</Frame_Bridge.description>
  
  
</LanguageData>
