<?xml version="1.0" encoding="utf-8"?>
<LanguageData>

  <PsychicEmanator.label>psychický vyzařovač</PsychicEmanator.label>
  <PsychicEmanator.description>An ancient device that projects a soothing psychic field around itself. This improves the mood of anyone nearby. Works through walls.</PsychicEmanator.description>
  <PsychicEmanator_Blueprint_Install.label>psychický vyzařovač (plán)</PsychicEmanator_Blueprint_Install.label>

  <VanometricPowerCell.label>vanometrický napájecí článek</VanometricPowerCell.label>
  <VanometricPowerCell.description>Generuje zdarma energii, navždy, bez použití paliva. Tato technologie je vyvinuta UI archotechu, a je mnohokrát lepší než kdejaké technologie vyspělých společností. I když nikdo přesně neví, jak to funguje, odborníci věří, že to nějak odebírá energii přímo z kolísání kvantové pěny.</VanometricPowerCell.description>
  <VanometricPowerCell_Blueprint_Install.label>vanometrický napájecí článek (plán)</VanometricPowerCell_Blueprint_Install.label>

  <InfiniteChemreactor.label>nekonečný chem-reaktor</InfiniteChemreactor.label>
  <InfiniteChemreactor.description>Pomalu generuje chemické palivo tím, že využívá složité série chemických reakcí, použitím extrakce atomů ze vzduchu.</InfiniteChemreactor.description>
  <InfiniteChemreactor_Blueprint_Install.label>nekonečný chem-reaktor (plán)</InfiniteChemreactor_Blueprint_Install.label>


</LanguageData>
