<?xml version="1.0" encoding="utf-8"?>
<LanguageData>

  <!-- Frag grenade -->

  <Weapon_GrenadeFrag.label>tříštivé granáty</Weapon_GrenadeFrag.label>
  <Weapon_GrenadeFrag.description>Tříštivé granáty jako za starých časů.</Weapon_GrenadeFrag.description>
  <Weapon_GrenadeFrag.verbs.0.label>Hodit tříštivý granát</Weapon_GrenadeFrag.verbs.0.label>

  <Proj_GrenadeFrag.label>trhavina</Proj_GrenadeFrag.label>


  <!-- Molotov cocktail -->

  <Weapon_GrenadeMolotov.label>molotovovy koktejly</Weapon_GrenadeMolotov.label>
  <Weapon_GrenadeMolotov.description>Skleněná láhev naplněná hořlavinou, která má v hrdle zastrčený zapálený kus látky. Oblíbená zbraň chuligánů a zoufalých bojovníků ve všech koutech vesmíru.</Weapon_GrenadeMolotov.description>
  <Weapon_GrenadeMolotov.verbs.0.label>Hodit Molotovův koktejl</Weapon_GrenadeMolotov.verbs.0.label>

  <Proj_GrenadeMolotov.label>zápalná láhev</Proj_GrenadeMolotov.label>


  <!-- EMP grenade -->

  <Weapon_GrenadeEMP.label>EMP granáty</Weapon_GrenadeEMP.label>
  <Weapon_GrenadeEMP.description>Elektromagnetické pulzy těchto granátů dokáží vyřadit elektrické obranné systémy, nebo na chvíli i mechanoidy.</Weapon_GrenadeEMP.description>
  <Weapon_GrenadeEMP.verbs.0.label>Hodit EMP granát</Weapon_GrenadeEMP.verbs.0.label>

  <Proj_GrenadeEMP.label>EMP zbraň</Proj_GrenadeEMP.label>


</LanguageData>
