<?xml version="1.0" encoding="UTF-8"?>
<LanguageData>
  
  <!-- EN: Depending on ritual quality, participants will get between {MINMOOD} and {MAXMOOD} mood for {MOODDAYS} days. -->
  <AttendedSpeech.description>V závislosti na kvalitě rituálu získají všichni zúčastnění na {replace: ​{MOODDAYS}​​; "​1​"-"1 den"; "​2​"-"2 dny"; "​3​"-"3 dny"; "​4​"-"4 dny"; "​{MOODDAYS}​"-"{MOODDAYS} dnů"} {MINMOOD} až {MAXMOOD} k náladě.</AttendedSpeech.description>
  <!-- EN: {PAWN_labelShort}'s social impact -->
  <AttendedSpeech.comps.0.label>Sociální vliv ({PAWN_labelShort})</AttendedSpeech.comps.0.label>
  <!-- EN: speaker's social impact -->
  <AttendedSpeech.comps.0.labelAbstract>sociální vliv řečníka</AttendedSpeech.comps.0.labelAbstract>
  <!-- EN: participant count -->
  <AttendedSpeech.comps.1.label>počet účastníků</AttendedSpeech.comps.1.label>
  <!-- EN: room impressiveness -->
  <AttendedSpeech.comps.2.label>působivost místnosti</AttendedSpeech.comps.2.label>
  <!-- EN: Terrible -->
  <AttendedSpeech.outcomeChances.0.label>Hrozný</AttendedSpeech.outcomeChances.0.label>
  <!-- EN: Uninspiring -->
  <AttendedSpeech.outcomeChances.1.label>Nezáživný</AttendedSpeech.outcomeChances.1.label>
  <!-- EN: Encouraging -->
  <AttendedSpeech.outcomeChances.2.label>Povzbuzující</AttendedSpeech.outcomeChances.2.label>
  <!-- EN: Inspirational -->
  <AttendedSpeech.outcomeChances.3.label>Inspirativní</AttendedSpeech.outcomeChances.3.label>
  
</LanguageData>