<?xml version="1.0" encoding="UTF-8"?>
<LanguageData>
  
  <!-- EN: install cochlear implant -->
  <InstallCochlearImplant.label>implantovat kochleární implantát</InstallCochlearImplant.label>
  <!-- EN: Install a cochlear implant. -->
  <InstallCochlearImplant.description>Provede implantaci kochleárního implantátu.</InstallCochlearImplant.description>
  <!-- EN: Installing cochlear implant. -->
  <InstallCochlearImplant.jobString>Provádí implantaci kochleárního implantátu.</InstallCochlearImplant.jobString>
  
  <!-- EN: install joywire -->
  <InstallJoywire.label>implantovat čip štěstí</InstallJoywire.label>
  <!-- EN: Install a joywire. -->
  <InstallJoywire.description>Provede implantaci čipu štěstí.</InstallJoywire.description>
  <!-- EN: Installing joywire. -->
  <InstallJoywire.jobString>Provádí implantaci čipu štěstí.</InstallJoywire.jobString>
  
  <!-- EN: install painstopper -->
  <InstallPainstopper.label>implantovat blokovač bolesti</InstallPainstopper.label>
  <!-- EN: Install a painstopper. -->
  <InstallPainstopper.description>Provede implantaci blokovače bolesti.</InstallPainstopper.description>
  <!-- EN: Installing painstopper. -->
  <InstallPainstopper.jobString>Provádí implantaci blokovače bolesti.</InstallPainstopper.jobString>
  
  <!-- EN: install power claw -->
  <InstallPowerClaw.label>implantovat energospár</InstallPowerClaw.label>
  <!-- EN: Install a power claw. -->
  <InstallPowerClaw.description>Provede implantaci energospáru.</InstallPowerClaw.description>
  <!-- EN: Installing power claw. -->
  <InstallPowerClaw.jobString>Provádí implantaci energospáru.</InstallPowerClaw.jobString>
  
  <!-- EN: install prosthetic arm -->
  <InstallSimpleProstheticArm.label>implantovat protetickou paži</InstallSimpleProstheticArm.label>
  <!-- EN: Install a prosthetic arm. -->
  <InstallSimpleProstheticArm.description>Provede implantaci protetické paže.</InstallSimpleProstheticArm.description>
  <!-- EN: Installing prosthetic arm. -->
  <InstallSimpleProstheticArm.jobString>Provádí implantaci protetické paže.</InstallSimpleProstheticArm.jobString>
  
  <!-- EN: install prosthetic heart -->
  <InstallSimpleProstheticHeart.label>implantovat umělé srdce</InstallSimpleProstheticHeart.label>
  <!-- EN: Install a prosthetic heart. -->
  <InstallSimpleProstheticHeart.description>Provede implantaci umělého srdce.</InstallSimpleProstheticHeart.description>
  <!-- EN: Installing prosthetic heart. -->
  <InstallSimpleProstheticHeart.jobString>Provádí implantaci umělého srdce.</InstallSimpleProstheticHeart.jobString>
  
  <!-- EN: install prosthetic leg -->
  <InstallSimpleProstheticLeg.label>implantovat protetickou nohu</InstallSimpleProstheticLeg.label>
  <!-- EN: Install a prosthetic leg. -->
  <InstallSimpleProstheticLeg.description>Provede implantaci protetické nohy.</InstallSimpleProstheticLeg.description>
  <!-- EN: Installing prosthetic leg. -->
  <InstallSimpleProstheticLeg.jobString>Provádí implantaci protetické nohy.</InstallSimpleProstheticLeg.jobString>
  
  <!-- EN: remove painstopper -->
  <RemovePainstopper.label>vyjmout blokovač bolesti</RemovePainstopper.label>
  <!-- EN: Remove the painstopper. -->
  <RemovePainstopper.description>Provede vyjmutí blokovače bolesti.</RemovePainstopper.description>
  <!-- EN: Removing painstopper. -->
  <RemovePainstopper.jobString>Provádí vyjmutí blokovače bolesti.</RemovePainstopper.jobString>
  
</LanguageData>