<?xml version="1.0" encoding="UTF-8"?>
<LanguageData>
  
  <!-- EN: hellcat rifle bullet -->
  <Bullet_HellcatRifle.label>střela z fúriina spalovače</Bullet_HellcatRifle.label>
  
  <!-- EN: hellcat rifle -->
  <Gun_HellcatRifle.label>fúriin spalovač</Gun_HellcatRifle.label>
  <!-- EN: A versatile assault rifle with good range, decent power, and good accuracy.\n\nIt also comes equipped with a bioferrite-powered mini-burner unit which generates a blast of flame from pressurized bioferrite charges. The mini-burner unit can be used twice before refueling. -->
  <Gun_HellcatRifle.description>Všestraná útočná puška s dobrým dostřelem, silnou ráží a dobrou přesností.\n\nJe vybaven bioferitovým plamenometem, který je schopný chrlit oheň spalováním bioferitových náplní. Tento plamenomet může být použitý dvakrát, před tím než musí být přebit.</Gun_HellcatRifle.description>
  <!-- EN: burner charge -->
  <Gun_HellcatRifle.comps.CompEquippableAbilityReloadable.chargeNoun>spalovací náplň</Gun_HellcatRifle.comps.CompEquippableAbilityReloadable.chargeNoun>
  <!-- EN: on cooldown -->
  <Gun_HellcatRifle.comps.CompEquippableAbilityReloadable.cooldownGerund>nabíjí se</Gun_HellcatRifle.comps.CompEquippableAbilityReloadable.cooldownGerund>
  <!-- EN: stock -->
  <Gun_HellcatRifle.tools.stock.label>pažba</Gun_HellcatRifle.tools.stock.label>
  <!-- EN: barrel -->
  <Gun_HellcatRifle.tools.barrel.label>hlaveň</Gun_HellcatRifle.tools.barrel.label>
  <!-- EN: hellcat rifle -->
  <Gun_HellcatRifle.verbs.Verb_Shoot.label>fúriin spalovač</Gun_HellcatRifle.verbs.Verb_Shoot.label>
  
  <!-- EN: incinerator -->
  <Gun_Incinerator.label>spalující hořák</Gun_Incinerator.label>
  <!-- EN: A heavy weapon that can spray a stream of flame into an area. It can shoot in an arc over allies without harming them. The flame burns off rapidly, so it will only ignite the most flammable targets.\n\nWhile the main flamethrower can be used without limit, the weapon also comes equipped with a bioferrite-powered mega-burner unit which generates a massive blast of flame from a pressurized bioferrite charge. The mega-burner unit must be refueled after each use. -->
  <Gun_Incinerator.description>Težká zbraň, která chrlí silný proud plamene. Jeho plamen je chrlen obloukem, což umožňuje ho použít i v případech, kdy před střelcem někdo stojí. Tento plamen hoří rapidní rychlostí, takže zapálí pouze velmi hořlavé cíle.\n\nZatím co jeho hlavní hořák muže být používán bez omezení, také má bioferitem poháněný megahořák, kterého použití vytvoří obří plamen. Tento megahořák musí být přebít po každém použití.</Gun_Incinerator.description>
  <!-- EN: burner charge -->
  <Gun_Incinerator.comps.CompEquippableAbilityReloadable.chargeNoun>spalovací náplň</Gun_Incinerator.comps.CompEquippableAbilityReloadable.chargeNoun>
  <!-- EN: on cooldown -->
  <Gun_Incinerator.comps.CompEquippableAbilityReloadable.cooldownGerund>nabíjí se</Gun_Incinerator.comps.CompEquippableAbilityReloadable.cooldownGerund>
  <!-- EN: stock -->
  <Gun_Incinerator.tools.stock.label>pažba</Gun_Incinerator.tools.stock.label>
  <!-- EN: barrel -->
  <Gun_Incinerator.tools.barrel.label>hlaveň</Gun_Incinerator.tools.barrel.label>
  <!-- EN: incinerator -->
  <Gun_Incinerator.verbs.Verb_ArcSprayIncinerator.label>spalující hořák</Gun_Incinerator.verbs.Verb_ArcSprayIncinerator.label>
  
</LanguageData>