<?xml version="1.0" encoding="utf-8"?>
<LanguageData>

  <PrisonCell.stages.0.label>Příšerná vězeňská cela</PrisonCell.stages.0.label>
  <PrisonCell.stages.0.description>Tato vězeňská cela je prostě hrozná.</PrisonCell.stages.0.description>
  <PrisonCell.stages.3.label>Slušná vězeňská cela</PrisonCell.stages.3.label>
  <PrisonCell.stages.3.description>Tato vězeňská cela je docela slušná.</PrisonCell.stages.3.description>
  <PrisonCell.stages.4.label>Mírně působivá vězeňská cela</PrisonCell.stages.4.label>
  <PrisonCell.stages.4.description>Tato vězeňská cela vypadá jako příjemné místo.</PrisonCell.stages.4.description>
  <PrisonCell.stages.5.label>Docela působivá vězeňská cela</PrisonCell.stages.5.label>
  <PrisonCell.stages.5.description>Tato vězeňská cela je docela působivá. Nemůžu uvěřit, že mě drží v místnosti jako je tahle.</PrisonCell.stages.5.description>
  <PrisonCell.stages.6.label>Velmi působivá vězeňská cela</PrisonCell.stages.6.label>
  <PrisonCell.stages.6.description>Tato vězeňská cela je velmi působivá. Nemůžu uvěřit, že mě drží v místnosti jako je tahle. Miluju to tady!</PrisonCell.stages.6.description>
  <PrisonCell.stages.7.label>Mimořádně působivá vězeňská cela</PrisonCell.stages.7.label>
  <PrisonCell.stages.7.description>Tato vězeňská cela je mimořádně působivá. Nemůžu uvěřit, že mě drží v místnosti jako je tahle. Miluju to tady!</PrisonCell.stages.7.description>
  <PrisonCell.stages.8.label>Neuvěřitelně působivá vězeňská cela</PrisonCell.stages.8.label>
  <PrisonCell.stages.8.description>Tato vězeňská cela je neuvěřitelně působivá. Tohle je to nejlepší místo na světě!</PrisonCell.stages.8.description>
  <PrisonCell.stages.9.label>Úžasně působivá vězeňská cela</PrisonCell.stages.9.label>
  <PrisonCell.stages.9.description>Tato vězeňská cela je to nejlepší místo, jaké si kdo dokáže představit. Tady bych zůstal navždy.</PrisonCell.stages.9.description>

  <PrisonBarracks.stages.0.label>Příšerná společná cela</PrisonBarracks.stages.0.label>
  <PrisonBarracks.stages.0.description>Tato společná cela je prostě hrozná.</PrisonBarracks.stages.0.description>
  <PrisonBarracks.stages.1.label>Fádní společná cela</PrisonBarracks.stages.1.label>
  <PrisonBarracks.stages.1.description>Tato společná cela je fádní.</PrisonBarracks.stages.1.description>
  <PrisonBarracks.stages.4.label>Mírně působivá společná cela</PrisonBarracks.stages.4.label>
  <PrisonBarracks.stages.4.description>Tato společná cela je mírně působivá.</PrisonBarracks.stages.4.description>
  <PrisonBarracks.stages.5.label>Docela působivá společná cela</PrisonBarracks.stages.5.label>
  <PrisonBarracks.stages.5.description>Tato společná cela je docela působivá. Líbí se mi.</PrisonBarracks.stages.5.description>
  <PrisonBarracks.stages.6.label>Velmi působivá společná cela</PrisonBarracks.stages.6.label>
  <PrisonBarracks.stages.6.description>Tato společná cela je velmi působivá. Líbí se mi.</PrisonBarracks.stages.6.description>
  <PrisonBarracks.stages.7.label>Mimořádně působivá společná cela</PrisonBarracks.stages.7.label>
  <PrisonBarracks.stages.7.description>Tato společná cela je mimořádně působivá. Nemůžu uvěřit, že mě drží v místnosti jako je tahle.</PrisonBarracks.stages.7.description>
  <PrisonBarracks.stages.8.label>Neuvěřitelně působivá společná cela</PrisonBarracks.stages.8.label>
  <PrisonBarracks.stages.8.description>Tato společná cela je neuvěřitelně působivá. Nemůžu uvěřit, že mě drží v místnosti jako je tahle.</PrisonBarracks.stages.8.description>
  <PrisonBarracks.stages.9.label>Úžasně působivá společná cela</PrisonBarracks.stages.9.label>
  <PrisonBarracks.stages.9.description>Tato společná cela je úžasná! Nemůžu uvěřit, že mě drží v místnosti jako je tahle.</PrisonBarracks.stages.9.description>

  <HospitalPatientRoomStats.stages.0.label>Příšerná nemocnice</HospitalPatientRoomStats.stages.0.label>
  <HospitalPatientRoomStats.stages.0.description>Tato nemocnice je prostě hrozná.</HospitalPatientRoomStats.stages.0.description>
  <HospitalPatientRoomStats.stages.1.label>Fádní nemocnice</HospitalPatientRoomStats.stages.1.label>
  <HospitalPatientRoomStats.stages.1.description>Tato nemocnice je fádní.</HospitalPatientRoomStats.stages.1.description>
  <HospitalPatientRoomStats.stages.4.label>Mírně působivá nemocnice</HospitalPatientRoomStats.stages.4.label>
  <HospitalPatientRoomStats.stages.4.description>Tato nemocnice je mírně působivá. Už se cítím trochu lépe.</HospitalPatientRoomStats.stages.4.description>
  <HospitalPatientRoomStats.stages.5.label>Docela působivá nemocnice</HospitalPatientRoomStats.stages.5.label>
  <HospitalPatientRoomStats.stages.5.description>Tato nemocnice je docela působivá. Už se cítím lépe.</HospitalPatientRoomStats.stages.5.description>
  <HospitalPatientRoomStats.stages.6.label>Velmi působivá nemocnice</HospitalPatientRoomStats.stages.6.label>
  <HospitalPatientRoomStats.stages.6.description>Tato nemocnice je velmi působivá. Už se cítím lépe.</HospitalPatientRoomStats.stages.6.description>
  <HospitalPatientRoomStats.stages.7.label>Mimořádně působivá nemocnice</HospitalPatientRoomStats.stages.7.label>
  <HospitalPatientRoomStats.stages.7.description>Tato nemocnice je mimořádně působivá. Už se cítím doopravdy lépe.</HospitalPatientRoomStats.stages.7.description>
  <HospitalPatientRoomStats.stages.8.label>Neuvěřitelně působivá nemocnice</HospitalPatientRoomStats.stages.8.label>
  <HospitalPatientRoomStats.stages.8.description>Tato nemocnice je neuvěřitelně působivá. Už se cítím doopravdy lépe.</HospitalPatientRoomStats.stages.8.description>
  <HospitalPatientRoomStats.stages.9.label>Úžasně působivá nemocnice</HospitalPatientRoomStats.stages.9.label>
  <HospitalPatientRoomStats.stages.9.description>Tato nemocnice je úžasná! Už se cítím doopravdy lépe.</HospitalPatientRoomStats.stages.9.description>


</LanguageData>