<?xml version="1.0" encoding="UTF-8"?>
<LanguageData>
  
  <!-- EN: ambush -->
  <Ambush.label>Léčka</Ambush.label>
  <!-- EN: Caravan ambushed -->
  <Ambush.letterLabel>Karavana byla přepadena</Ambush.letterLabel>
  <!-- EN: {0} has been ambushed by {1} from {2}! -->
  <Ambush.letterText>{0} byla přepadena skupinou {1} z frakce {2}!</Ambush.letterText>
  
  <!-- EN: payment demand -->
  <CaravanDemand.label>Požadování výpalného</CaravanDemand.label>
  
  <!-- EN: caravan meeting -->
  <CaravanMeeting.label>Setkání karavan</CaravanMeeting.label>
  
  <!-- EN: manhunter ambush -->
  <ManhunterAmbush.label>Přepadení lidožravou smečkou</ManhunterAmbush.label>
  <!-- EN: Caravan ambushed (manhunters) -->
  <ManhunterAmbush.letterLabel>Karavana byla přepadena (smečka lidojedů)</ManhunterAmbush.letterLabel>
  <!-- EN: {0} has been ambushed by manhunting {1}! -->
  <ManhunterAmbush.letterText>{0} byla přepadena smečkou lidožravé zvěře ({1})!</ManhunterAmbush.letterText>
  
</LanguageData>