<?xml version="1.0" encoding="UTF-8"?>
<LanguageData>
  
  <!-- EN: alphabeavers -->
  <Alphabeavers.label>alfa bobři</Alphabeavers.label>
  
  <!-- EN: ambrosia sprout -->
  <AmbrosiaSprout.label>ambrozie klíčí</AmbrosiaSprout.label>
  <!-- EN: Ambrosia sprout -->
  <AmbrosiaSprout.letterLabel>Ambrozie klíčí</AmbrosiaSprout.letterLabel>
  <!-- EN: A grove of the mysterious ambrosia bush has sprouted nearby! If you wait for the plants to grow, you'll be able to harvest the delicious, pleasurable, and slightly addictive fruit. -->
  <AmbrosiaSprout.letterText>Poblíž se vynořil klíček záhadného ambrozového křoviska! Pokud počkáš, až rostlina vyroste, budeš ji moci sklidit pro příjemně lahodné a mírně návykové plody.</AmbrosiaSprout.letterText>
  
  <!-- EN: cold snap -->
  <ColdSnap.label>prudké ochlazení</ColdSnap.label>
  <!-- EN: Cold snap -->
  <ColdSnap.letterLabel>Prudké ochlazení</ColdSnap.letterLabel>
  
  <!-- EN: crop blight -->
  <CropBlight.label>plíseň</CropBlight.label>
  
  <!-- EN: farm animals wander in -->
  <FarmAnimalsWanderIn.label>hospodářská zvířata se přitoulala</FarmAnimalsWanderIn.label>
  
  <!-- EN: flashstorm -->
  <Flashstorm.label>extrémní smršť blesků</Flashstorm.label>
  <!-- EN: Flashstorm -->
  <Flashstorm.letterLabel>Extrémní smršť blesků</Flashstorm.letterLabel>
  
  <!-- EN: heat wave -->
  <HeatWave.label>vlna veder</HeatWave.label>
  <!-- EN: Heat wave -->
  <HeatWave.letterLabel>Vlna veder</HeatWave.letterLabel>
  
  <!-- EN: herd migration -->
  <HerdMigration.label>migrace stáda</HerdMigration.label>
  <!-- EN: Animal migration: {0} -->
  <HerdMigration.letterLabel>Migrace zvířat</HerdMigration.letterLabel>
  <!-- EN: A group of {0} is passing through the area.\n\nThey won't attack unless provoked. -->
  <HerdMigration.letterText>Oblastí prochází skupina {0}.\n\nZvířata nezaútočí, pokud k tomu nebudou vyprovokována.</HerdMigration.letterText>
  
  <!-- EN: meteorite impact -->
  <MeteoriteImpact.label>dopad meteoritu</MeteoriteImpact.label>
  <!-- EN: Meteorite -->
  <MeteoriteImpact.letterLabel>Meteorit</MeteoriteImpact.letterLabel>
  <!-- EN: A large meteorite has struck ground in the area. It has left behind a lump of {0}. -->
  <MeteoriteImpact.letterText>Velký meteorit zasáhl zemi v této oblasti. Zanechal tu nějakou hroudu ({0}).</MeteoriteImpact.letterText>
  
  <!-- EN: psychic drone -->
  <PsychicDrone.label>psychické bzučení</PsychicDrone.label>
  
  <!-- EN: psychic soothe -->
  <PsychicSoothe.label>psychické uklidnění</PsychicSoothe.label>
  
  <!-- EN: ransom demand -->
  <RansomDemand.label>požadování výkupného</RansomDemand.label>
  <!-- EN: Ransom demand -->
  <RansomDemand.letterLabel>Požadování výkupného</RansomDemand.letterLabel>
  
  <!-- EN: transport pod crash -->
  <RefugeePodCrash.label>zřícení přepravního modulu</RefugeePodCrash.label>
  
  <!-- EN: resource pod crash -->
  <ResourcePodCrash.label>zřícení modulu se surovinami</ResourcePodCrash.label>
  
  <!-- EN: self-tame -->
  <SelfTame.label>samovolné ochočení</SelfTame.label>
  
  <!-- EN: short circuit -->
  <ShortCircuit.label>zkrat</ShortCircuit.label>
  
  <!-- EN: thrumbos pass -->
  <ThrumboPasses.label>prochází Thrumbové</ThrumboPasses.label>
  
  <!-- EN: toxic fallout -->
  <ToxicFallout.label>toxický spad</ToxicFallout.label>
  <!-- EN: Toxic fallout -->
  <ToxicFallout.letterLabel>Toxický spad</ToxicFallout.letterLabel>
  
  <!-- EN: volcanic winter -->
  <VolcanicWinter.label>vulkanická zima</VolcanicWinter.label>
  <!-- EN: Volcanic winter -->
  <VolcanicWinter.letterLabel>Vulkanická zima</VolcanicWinter.letterLabel>
  
  <!-- EN: wanderer join -->
  <WandererJoin.label>poutník se připojil</WandererJoin.label>
  <!-- EN: Wanderer joins: {PAWN_nameDef} -->
  <WandererJoin.letterLabel>{PAWN_gender ? Poutník : Poutnice} {PAWN_nameDef} se {PAWN_gender ? připojil : připojila}</WandererJoin.letterLabel>
  <!-- EN: A {PAWN_title} named {PAWN_nameDef} has arrived and is joining the colony.\n\n[PAWN_pronoun] is willing to contribute, but will not leave voluntarily. If you don't want {PAWN_nameDef}, you can banish {PAWN_objective}, sell {PAWN_objective} into slavery, or simply kill {PAWN_objective}. However, your other colonists may find this disturbing. -->
  <WandererJoin.letterText>{PAWN_title} jménem {PAWN_nameDef} {PAWN_gender ? dorazil : dorazila} a {PAWN_gender ? připojil : připojila} se ke kolonii. Je to {PAWN_title}.\n\n{PAWN_gender ? Chtěl : Chtěla} by něčím přispět, z vlastní vůle však neodejde. Pokud nechceš, aby {PAWN_gender ? zůstal : zůstala}, můžeš {PAWN_objective} vyhostit, prodat do otroctví, nebo prostě zabít. Nicméně ostatní kolonisté z toho mohou být znepokojeni.</WandererJoin.letterText>
  
  <!-- EN: wild man wanders in -->
  <WildManWandersIn.label>divoch bloudí oblastí</WildManWandersIn.label>
  <!-- EN: {PAWN_kind} wanders in -->
  <WildManWandersIn.letterLabel>{PAWN_kind} bloudí oblastí</WildManWandersIn.letterLabel>
  <!-- EN: A person living among wild animals has wandered into the area. {PAWN_pronoun}'s called {0}.\n\nYou can attempt to tame or arrest {PAWN_objective}. -->
  <WildManWandersIn.letterText>Do této oblasti se {PAWN_gender ? zatoulal : zatoulala} {PAWN_gender} žijící mezi divokými zvířaty. Dříve {PAWN_gender ? mu : ji} říkali {0}.\n\nMůžeš se {PAWN_objective} pokusit ochočit nebo zadržet.</WildManWandersIn.letterText>
  
</LanguageData>