<?xml version="1.0" encoding="utf-8"?>
<LanguageData>

  <!-- Install natural parts -->

  <InstallNaturalKidney.label>implantace ledviny</InstallNaturalKidney.label>
  <InstallNaturalKidney.description>Provede implantaci ledviny.</InstallNaturalKidney.description>
  <InstallNaturalKidney.jobString>Provádí implantaci ledviny.</InstallNaturalKidney.jobString>

  <InstallNaturalLiver.label>implantace jater</InstallNaturalLiver.label>
  <InstallNaturalLiver.description>Provede implantaci jater.</InstallNaturalLiver.description>
  <InstallNaturalLiver.jobString>Provádí implantaci jater.</InstallNaturalLiver.jobString>

  <InstallNaturalLung.label>implantace plíce</InstallNaturalLung.label>
  <InstallNaturalLung.description>Provede implantaci plíce.</InstallNaturalLung.description>
  <InstallNaturalLung.jobString>Provádí implantaci plíce.</InstallNaturalLung.jobString>

  <InstallNaturalHeart.label>implantace srdce</InstallNaturalHeart.label>
  <InstallNaturalHeart.description>Provede implantaci srdce.</InstallNaturalHeart.description>
  <InstallNaturalHeart.jobString>Provádí implantaci srdce.</InstallNaturalHeart.jobString>


  <!-- Install artificial parts -->

  <InstallPegLeg.label>implantace dřevěné nohy</InstallPegLeg.label>
  <InstallPegLeg.description>Provede implantaci dřevěné nohy.</InstallPegLeg.description>
  <InstallPegLeg.jobString>Provádí implantaci dřevěné nohy.</InstallPegLeg.jobString>

  <InstallDenture.label>implantace zubní protézy</InstallDenture.label>
  <InstallDenture.description>Provede implantaci zubní protézy.</InstallDenture.description>
  <InstallDenture.jobString>Provádí implantaci zubní protézy.</InstallDenture.jobString>

  <InstallSimpleProstheticLeg.label>implantace jednoduché protézy nohy</InstallSimpleProstheticLeg.label>
  <InstallSimpleProstheticLeg.description>Provede implantaci jednoduché protézy nohy.</InstallSimpleProstheticLeg.description>
  <InstallSimpleProstheticLeg.jobString>Provádí implantaci jednoduché protézy nohy.</InstallSimpleProstheticLeg.jobString>

  <InstallSimpleProstheticArm.label>implantace jednoduché protézy paže</InstallSimpleProstheticArm.label>
  <InstallSimpleProstheticArm.description>Provede implantaci jednoduché protézy paže.</InstallSimpleProstheticArm.description>
  <InstallSimpleProstheticArm.jobString>Provádí implantaci jednoduché protézy paže.</InstallSimpleProstheticArm.jobString>

  <InstallBionicArm.label>implantace bionické paže</InstallBionicArm.label>
  <InstallBionicArm.description>Provede implantaci bionické paže.</InstallBionicArm.description>
  <InstallBionicArm.jobString>Provádí implantaci bionické paže.</InstallBionicArm.jobString>

  <InstallBionicLeg.label>implantace bionické nohy</InstallBionicLeg.label>
  <InstallBionicLeg.description>Provede implantaci bionické nohy.</InstallBionicLeg.description>
  <InstallBionicLeg.jobString>Provádí implantaci bionické nohy.</InstallBionicLeg.jobString>

  <InstallPowerClaw.label>implantace energospáru</InstallPowerClaw.label>
  <InstallPowerClaw.description>Provede implantaci energospáru.</InstallPowerClaw.description>
  <InstallPowerClaw.jobString>Provádí implantaci energospáru.</InstallPowerClaw.jobString>

  <InstallScytherBlade.label>implantace smrťákové čepele</InstallScytherBlade.label>
  <InstallScytherBlade.description>Provede implantaci smrťákové čepele.</InstallScytherBlade.description>
  <InstallScytherBlade.jobString>Provádí implantaci smrťákové čepele.</InstallScytherBlade.jobString>

  <InstallBionicEye.label>implantace bionického oka</InstallBionicEye.label>
  <InstallBionicEye.description>Provede implantaci bionického oka.</InstallBionicEye.description>
  <InstallBionicEye.jobString>Provádí implantaci bionického oka.</InstallBionicEye.jobString>

  <InstallJoywire.label>implantace implantátu Joywire</InstallJoywire.label>
  <InstallJoywire.description>Provede implantaci implantátu Joywire.</InstallJoywire.description>
  <InstallJoywire.jobString>Provádí implantaci implantátu Joywire.</InstallJoywire.jobString>

  <InstallPainstopper.label>implantace blokovače bolesti</InstallPainstopper.label>
  <InstallPainstopper.description>Provede implantaci blokovače bolesti.</InstallPainstopper.description>
  <InstallPainstopper.jobString>Provádí implantaci blokovače bolesti.</InstallPainstopper.jobString>


</LanguageData>