<?xml version="1.0" encoding="utf-8"?>
<LanguageData>

  <Clear.label>jasno</Clear.label>
  <Clear.description>Krásný jasný den. Žádné postihy nebo modifikátory.</Clear.description>

  <Fog.label>mlha</Fog.label>
  <Fog.description>Mlha snižuje přesnost zbraní na dálku.</Fog.description>

  <Rain.label>déšť</Rain.label>
  <Rain.description>Déšť snižuje přesnost zbraní na dálku, hasí oheň a zpomaluje pohyb lidí.</Rain.description>

  <DryThunderstorm.label>bouřka bez deště</DryThunderstorm.label>
  <DryThunderstorm.description>Bouřky bez deště jsou velmi nebezpečné, protože blesky mohou způsobit rozsáhlé požáry, které se bez deště stěží uhasí.</DryThunderstorm.description>

  <RainyThunderstorm.label>bouřka s deštěm</RainyThunderstorm.label>
  <RainyThunderstorm.description>Blesky zakládají požáry, které déšť bude bez problémů hasit. Bouřka současně snižuje přesnost zbraní na dálku a zpomaluje pohyb lidí.</RainyThunderstorm.description>

  <FoggyRain.label>mlha s deštěm</FoggyRain.label>
  <FoggyRain.description>Snižuje přesnost a rychlost pohybu.</FoggyRain.description>

  <SnowHard.label>sněhová vánice</SnowHard.label>
  <SnowHard.description>Sněžení snižuje přesnost zbraní na dálku, hasí oheň a zpomaluje pohyb lidí.</SnowHard.description>

  <SnowGentle.label>sněhová přeháňka</SnowGentle.label>
  <SnowGentle.description>Sněžení snižuje přesnost zbraní na dálku, hasí oheň a zpomaluje pohyb lidí.</SnowGentle.description>


</LanguageData>