<?xml version="1.0" encoding="UTF-8"?>
<LanguageData>
  
  <!-- EN: Armor - Blunt -->
  <StuffPower_Armor_Blunt.label>Odolnost zbroje - tupé</StuffPower_Armor_Blunt.label>
  <!-- EN: Armor against blunt damage like club impacts, rock falls, and explosions. -->
  <StuffPower_Armor_Blunt.description>Hodnota odolnosti zbroje proti tupým poškozením, jako jsou údery kyjem, padající kameny, a exploze.</StuffPower_Armor_Blunt.description>
  
  <!-- EN: Armor - Heat -->
  <StuffPower_Armor_Heat.label>Odolnost zbroje - tepelné</StuffPower_Armor_Heat.label>
  <!-- EN: Armor against temperature-related damage like burns. -->
  <StuffPower_Armor_Heat.description>Hodnota odolnosti zbroje proti tepelným poškozením, jako jsou popáleniny.</StuffPower_Armor_Heat.description>
  
  <!-- EN: Armor - Sharp -->
  <StuffPower_Armor_Sharp.label>Odolnost zbroje - ostré</StuffPower_Armor_Sharp.label>
  <!-- EN: Armor against sharp damage like bullets, knife stabs, and animal bites. -->
  <StuffPower_Armor_Sharp.description>Hodnota odolnosti zbroje proti ostrým poškozením, jako jsou projektily, bodnutí nožem, a zvířecí pokousání.</StuffPower_Armor_Sharp.description>
  
  <!-- EN: Insulation - Cold -->
  <StuffPower_Insulation_Cold.label>Izolace zbroje - chlad</StuffPower_Insulation_Cold.label>
  <!-- EN: How much an apparel made of this material improves a wearer's minimum comfortable temperature when worn. -->
  <StuffPower_Insulation_Cold.description>Hodnota izolace, o kolik tento oděv, vyrobený z tohoto materiálu, vylepší minimální příjemnou teplotu nositele.</StuffPower_Insulation_Cold.description>
  
  <!-- EN: Insulation - Heat -->
  <StuffPower_Insulation_Heat.label>Izolace zbroje - teplo</StuffPower_Insulation_Heat.label>
  <!-- EN: How much an apparel made of this material improves a wearer's maximum comfortable temperature when worn. -->
  <StuffPower_Insulation_Heat.description>Hodnota izolace, o kolik tento oděv, vyrobený z tohoto materiálu, vylepší maximální příjemnou teplotu nositele.</StuffPower_Insulation_Heat.description>
  
</LanguageData>